topsis/__init__.py
topsis/__main__.py
topsis_Akshit_102183035-0.0.3.dist-info/LICENSE
topsis_Akshit_102183035-0.0.3.dist-info/METADATA
topsis_Akshit_102183035-0.0.3.dist-info/WHEEL
topsis_Akshit_102183035-0.0.3.dist-info/top_level.txt
topsis_Akshit_102183035-0.0.3.dist-info/RECORD
