Metadata-Version: 2.1
Name: topsis-Akshit-102183035
Version: 0.0.3
Summary: topsis-algo
Home-page: https://github.com/akshitmehrotra/Topsis
Author: Akshit
Author-email: akshitmehrotra28@example.com
Project-URL: Bug Tracker, https://github.com/akshitmehrotra/Topsis
Classifier: Programming Language :: Python :: 3
Classifier: License :: OSI Approved :: MIT License
Classifier: Operating System :: OS Independent
Requires-Python: >=3.6
License-File: LICENSE
